openbridge/__init__.py
openbridge/cli.py
openbridge/command.py
openbridge/config.py
openbridge/models.py
openbridge/proxy.py
openbridge/server.py
openbridge/templates.py
openbridge-0.1.0.dist-info/METADATA
openbridge-0.1.0.dist-info/WHEEL
openbridge-0.1.0.dist-info/entry_points.txt
openbridge-0.1.0.dist-info/top_level.txt
openbridge-0.1.0.dist-info/RECORD
